llm_memory/__init__.py
llm_memory/backends.py
llm_memory/core.py
llm_long_term_memory-0.1.0.dist-info/METADATA
llm_long_term_memory-0.1.0.dist-info/WHEEL
llm_long_term_memory-0.1.0.dist-info/licenses/LICENSE
llm_long_term_memory-0.1.0.dist-info/RECORD
