Metadata-Version: 2.4
Name: llm-long-term-memory
Version: 0.1.0
Summary: Give your AI agents persistent, searchable long-term memory with pluggable storage backends
Project-URL: Homepage, https://github.com/Devparihar5/llm-long-term-memory
Project-URL: Documentation, https://github.com/Devparihar5/llm-long-term-memory#readme
Project-URL: Repository, https://github.com/Devparihar5/llm-long-term-memory.git
Project-URL: Issues, https://github.com/Devparihar5/llm-long-term-memory/issues
Project-URL: Changelog, https://github.com/Devparihar5/llm-long-term-memory/releases
Author-email: Devendra Parihar <devendraparihar340@gmail.com>
Maintainer-email: Devendra Parihar <devendraparihar340@gmail.com>
License: MIT
License-File: LICENSE
Keywords: ai-agents,chatbot,faiss,langchain,llm,long-term-memory,memory,openai,rag,vector-search
Classifier: Development Status :: 4 - Beta
Classifier: Intended Audience :: Developers
Classifier: License :: OSI Approved :: MIT License
Classifier: Operating System :: OS Independent
Classifier: Programming Language :: Python :: 3
Classifier: Programming Language :: Python :: 3.8
Classifier: Programming Language :: Python :: 3.9
Classifier: Programming Language :: Python :: 3.10
Classifier: Programming Language :: Python :: 3.11
Classifier: Programming Language :: Python :: 3.12
Classifier: Topic :: Scientific/Engineering :: Artificial Intelligence
Classifier: Topic :: Software Development :: Libraries :: Python Modules
Requires-Python: >=3.8
Requires-Dist: faiss-cpu>=1.7.4
Requires-Dist: langchain-openai>=0.0.5
Requires-Dist: langchain>=0.1.0
Requires-Dist: numpy>=1.24.0
Requires-Dist: openai>=1.0.0
Requires-Dist: pydantic>=2.0.0
Provides-Extra: all
Requires-Dist: psycopg2-binary>=2.9.0; extra == 'all'
Requires-Dist: pymongo>=4.0.0; extra == 'all'
Requires-Dist: redis>=4.0.0; extra == 'all'
Provides-Extra: dev
Requires-Dist: black>=23.0.0; extra == 'dev'
Requires-Dist: isort>=5.0.0; extra == 'dev'
Requires-Dist: mypy>=1.0.0; extra == 'dev'
Requires-Dist: pytest-cov>=4.0.0; extra == 'dev'
Requires-Dist: pytest>=7.0.0; extra == 'dev'
Provides-Extra: mongodb
Requires-Dist: pymongo>=4.0.0; extra == 'mongodb'
Provides-Extra: postgresql
Requires-Dist: psycopg2-binary>=2.9.0; extra == 'postgresql'
Provides-Extra: redis
Requires-Dist: redis>=4.0.0; extra == 'redis'
Provides-Extra: streamlit
Requires-Dist: streamlit>=1.30.0; extra == 'streamlit'
